simple_ubl_invoice_generator/__init__.py
simple_ubl_invoice_generator/__main__.py
simple_ubl_invoice_generator/cli.py
simple_ubl_invoice_generator/generator.py
simple_ubl_invoice_generator/schema.py
simple_ubl_invoice_generator/template.xml
simple_ubl_invoice_generator/utils.py
simple_ubl_invoice_generator-0.4.1.dist-info/AUTHORS.rst
simple_ubl_invoice_generator-0.4.1.dist-info/LICENSE
simple_ubl_invoice_generator-0.4.1.dist-info/METADATA
simple_ubl_invoice_generator-0.4.1.dist-info/WHEEL
simple_ubl_invoice_generator-0.4.1.dist-info/entry_points.txt
simple_ubl_invoice_generator-0.4.1.dist-info/top_level.txt
simple_ubl_invoice_generator-0.4.1.dist-info/RECORD
