Metadata-Version: 2.1
Name: simple-ubl-invoice-generator
Version: 0.4.1
Summary: An example package. Generated with cookiecutter-pylibrary.
Home-page: https://github.com/ionelmc/python-simple-ubl-invoice-generator
Author: Ionel Cristian Mărieș
Author-email: contact@ionelmc.ro
License: BSD-2-Clause
Project-URL: Changelog, https://github.com/ionelmc/python-simple-ubl-invoice-generator/blob/master/CHANGELOG.rst
Project-URL: Issue Tracker, https://github.com/ionelmc/python-simple-ubl-invoice-generator/issues
Classifier: Development Status :: 5 - Production/Stable
Classifier: Intended Audience :: Developers
Classifier: License :: OSI Approved :: BSD License
Classifier: Operating System :: Unix
Classifier: Operating System :: POSIX
Classifier: Operating System :: Microsoft :: Windows
Classifier: Programming Language :: Python
Classifier: Programming Language :: Python :: 3
Classifier: Programming Language :: Python :: 3 :: Only
Classifier: Programming Language :: Python :: 3.11
Classifier: Programming Language :: Python :: 3.12
Classifier: Programming Language :: Python :: Implementation :: CPython
Classifier: Programming Language :: Python :: Implementation :: PyPy
Classifier: Topic :: Utilities
Requires-Python: >=3.11
License-File: LICENSE
License-File: AUTHORS.rst
Requires-Dist: pydantic
Requires-Dist: jinja2
